README.rst
setup.py
pycas/__init__.py
pycas/pycas.py
pycas.egg-info/PKG-INFO
pycas.egg-info/SOURCES.txt
pycas.egg-info/dependency_links.txt
pycas.egg-info/requires.txt
pycas.egg-info/top_level.txt