Metadata-Version: 1.1
Name: pycas
Version: 0.0.2
Summary: A pypi-downloadable version of Jon Rifkin's pycas client.
Home-page: https://github.com/ryanfox/pycas
Author: Ryan Fox
Author-email: ryan@foxrow.com
License: Apache 2.0
Keywords: CAS authentication
Platform: UNKNOWN
Classifier: Topic :: System :: Systems Administration :: Authentication/Directory
Classifier: Topic :: Utilities
Classifier: License :: OSI Approved :: Apache Software License
